mesh_client/__init__.py
mesh_client/io_helpers.py
mesh_client/key_helper.py
mesh_client/mesh_auth.py
mesh_client/nhs-dep-ca-bundle.pem
mesh_client/nhs-int-ca-bundle.pem
mesh_client/nhs-live-ca-bundle.pem
mesh_client/py.typed
mesh_client/types.py
mesh_client-5.0.1.dist-info/licenses/LICENSE
mesh_client-5.0.1.dist-info/METADATA
mesh_client-5.0.1.dist-info/WHEEL
mesh_client-5.0.1.dist-info/entry_points.txt
mesh_client-5.0.1.dist-info/top_level.txt
mesh_client-5.0.1.dist-info/RECORD
