Metadata-Version: 2.4
Name: Mesh-Client
Version: 5.0.1
Summary: Client for NHS England's MESH messaging system
Home-page: https://github.com/NHSDigital/mesh-client
Author: spinecore
License: MIT
Classifier: Programming Language :: Python :: 3.10
Classifier: Programming Language :: Python :: 3.11
Classifier: Programming Language :: Python :: 3.12
Classifier: Programming Language :: Python :: 3.13
Classifier: Programming Language :: Python :: 3.14
Requires-Python: >=3.10,<3.15.0
License-File: LICENSE
Requires-Dist: urllib3>=1.25.4
Requires-Dist: requests<3.0.0,>=2.32.0
Requires-Dist: werkzeug<4.0.0,>=3.0.3
Dynamic: author
Dynamic: classifier
Dynamic: description
Dynamic: description-content-type
Dynamic: home-page
Dynamic: license
Dynamic: license-file
Dynamic: requires-dist
Dynamic: requires-python
Dynamic: summary
